morpholib/__init__.py
morpholib/actions.py
morpholib/anim.py
morpholib/base.py
morpholib/bezier.py
morpholib/calculus.py
morpholib/color.py
morpholib/combo.py
morpholib/figure.py
morpholib/gadgets.py
morpholib/giffer.py
morpholib/graph.py
morpholib/graphics.py
morpholib/grid.py
morpholib/latex.py
morpholib/matrix.py
morpholib/sample.py
morpholib/shapes.py
morpholib/text.py
morpholib/transitions.py
morpholib/video.py
morpholib/tools/__init__.py
morpholib/tools/base.py
morpholib/tools/basics.py
morpholib/tools/color.py
morpholib/tools/dev.py
morpholib/tools/img.py
morpholib/tools/ktimer.py
morpholib/tools/latex2svg.py
morpholib/tools/subimporter.py
morpholib-0.11.0.dist-info/LICENSE
morpholib-0.11.0.dist-info/METADATA
morpholib-0.11.0.dist-info/WHEEL
morpholib-0.11.0.dist-info/top_level.txt
morpholib-0.11.0.dist-info/RECORD
