Metadata-Version: 2.1
Name: morpholib
Version: 0.11.0
Summary: A general-purpose programmatic animation tool
Home-page: https://github.com/morpho-matters/morpholib
Author: Kenneth Small
Author-email: morpho.matters@gmail.com
License: MIT
Classifier: Programming Language :: Python :: 3
Requires-Python: >=3.8
License-File: LICENSE
Requires-Dist: numpy<2.0
Requires-Dist: pillow
Requires-Dist: imageio<3.0
Requires-Dist: pyglet<2.0
Requires-Dist: pycairo<2.0
Requires-Dist: pyperclip<2.0
Requires-Dist: svgelements>=1.5.4
